guessfilename/__init__.py
guessfilename/guessfilenameconfig-TEMPLATE.py
guessfilename-2023.2.5.2.dist-info/LICENSE.txt
guessfilename-2023.2.5.2.dist-info/METADATA
guessfilename-2023.2.5.2.dist-info/WHEEL
guessfilename-2023.2.5.2.dist-info/entry_points.txt
guessfilename-2023.2.5.2.dist-info/top_level.txt
guessfilename-2023.2.5.2.dist-info/RECORD
