Metadata-Version: 2.1
Name: guessfilename
Version: 2023.2.5.2
Summary: Derive a file name according to old file name cues and/or PDF file content
Home-page: https://github.com/novoid/guess-filename.py
Download-URL: https://github.com/novoid/guess-filename.py/zipball/master
Author: Karl Voit
Author-email: tools@Karl-Voit.at
Keywords: file managing,file management,files,date,time,time-stamps
Classifier: Programming Language :: Python :: 3 :: Only
Classifier: Development Status :: 5 - Production/Stable
Classifier: Environment :: Console
Classifier: Intended Audience :: End Users/Desktop
Classifier: License :: OSI Approved :: GNU General Public License (GPL)
Classifier: Operating System :: OS Independent
License-File: LICENSE.txt
Requires-Dist: PyPDF2
Requires-Dist: colorama
Requires-Dist: fuzzywuzzy
Requires-Dist: pyexiftool
Requires-Dist: python-Levenshtein
